light_hf_proxy/__init__.py
light_hf_proxy-0.0.4.dist-info/LICENSE
light_hf_proxy-0.0.4.dist-info/METADATA
light_hf_proxy-0.0.4.dist-info/WHEEL
light_hf_proxy-0.0.4.dist-info/top_level.txt
light_hf_proxy-0.0.4.dist-info/RECORD
