Metadata-Version: 2.1
Name: light-hf-proxy
Version: 0.0.4
Summary: A light proxy solution for HuggingFace hub.
Author-email: Yemin Shi <shiyemin2@gmail.com>
License: Apache License
Project-URL: Homepage, https://github.com/shiyemin/light-hf-proxy
Project-URL: Bug Tracker, https://github.com/shiyemin/light-hf-proxy/issues
Classifier: Programming Language :: Python :: 3
Classifier: License :: OSI Approved :: Apache Software License
Classifier: Operating System :: OS Independent
Requires-Python: >=3.7
License-File: LICENSE
Requires-Dist: huggingface-hub
